{
    "version":"2025.03.18",
    "region":"Global",
    "lists":{
        "ServerZoneIpcType":{
            "PlayerSpawn":817,
            "NpcSpawn":319,
            "NpcSpawn2":771,
            "ActorFreeSpawn":144,
            "ObjectSpawn":969,
            "ObjectDespawn":390,
            "CreateTreasure":365,
            "OpenTreasure":776,
            "TreasureFadeOut":702,
            "ActorMove":345,
            "Transfer":161,
            "Effect":785,
            "AoeEffect8":558,
            "AoeEffect16":301,
            "AoeEffect24":783,
            "AoeEffect32":816,
            "ActorCast":378,
            "ActorControl":520,
            "ActorControlTarget":224,
            "ActorControlSelf":367,
            "DirectorVars":743,
            "EnvironmentControl":242,
            "_record_unk29_":779,
            "LandSetMap":772,
            "_record_unk31_":718,
            "EventStart":955,
            "EventFinish":582,
            "EventPlay":991,
            "EventPlay4":126,
            "EventPlay8":551,
            "EventPlay16":129,
            "EventPlay32":789,
            "EventPlay64":767,
            "EventPlay128":230,
            "EventPlay255":467,
            "BattleTalk2":541,
            "BattleTalk4":948,
            "BattleTalk8":562,
            "BalloonTalk2":195,
            "BalloonTalk4":344,
            "BalloonTalk8":600,
            "SystemLogMessage":642,
            "SystemLogMessage32":435,
            "SystemLogMessage48":264,
            "SystemLogMessage80":916,
            "SystemLogMessage144":835,
            "NpcYell":443,
            "ActorSetPos":136,
            "PrepareZoning":364,
            "WeatherChange":373,
            "UpdateParty":879,
            "UpdateAlliance":166,
            "UpdateSpAlliance":491,
            "UpdateHpMpTp":325,
            "StatusEffectList":839,
            "StatusEffectList2":708,
            "StatusEffectList3":711,
            "EurekaStatusEffectList":908,
            "BossStatusEffectList":350,
            "EffectResult":891,
            "EffectResult4":258,
            "EffectResult8":929,
            "EffectResult16":995,
            "EffectResultBasic":800,
            "EffectResultBasic4":883,
            "EffectResultBasic8":312,
            "EffectResultBasic16":861,
            "EffectResultBasic32":336,
            "EffectResultBasic64":184,
            "PartyPos":352,
            "AlliancePos":493,
            "SpAlliancePos":200,
            "PlaceMarker":830,
            "PlaceFieldMarkerPreset":413,
            "PlaceFieldMarker":569,
            "ActorGauge":946,
            "CharaVisualEffect":720,
            "Fall":707,
            "UpdateHate":704,
            "UpdateHater":366,
            "FirstAttack":293,
            "ModelEquip":158,
            "EquipDisplayFlags":523,
            "UnMount":228,
            "Mount":487,
            "PlayMotionSync":649,
            "CountdownInitiate":894,
            "CountdownCancel":128,
            "InitZone":699,
            "Examine":135,
            "ExamineSearchInfo":599,
            "InventoryActionAck":262,
            "MarketBoardItemListing":465,
            "MarketBoardItemListingCount":157,
            "MarketBoardItemListingHistory":782,
            "MarketBoardSearchResult":310,
            "MarketBoardPurchase":415,
            "PlayerSetup":218,
            "PlayerStats":401,
            "Playtime":577,
            "UpdateClassInfo":119,
            "UpdateInventorySlot":280,
            "UpdateSearchInfo":199,
            "WardLandInfo":970,
            "CEDirector":182,
            "Logout":105,
            "FreeCompanyInfo":447,
            "FreeCompanyDialog":624,
            "AirshipStatusList":987,
            "AirshipStatus":832,
            "AirshipExplorationResult":670,
            "SubmarineStatusList":214,
            "SubmarineProgressionStatus":549,
            "SubmarineExplorationResult":118,
            "CFPreferredRole":656,
            "CompanyAirshipStatus":907,
            "CompanySubmersibleStatus":576,
            "ContentFinderNotifyPop":557,
            "FateInfo":726,
            "UpdateRecastTimes":335,
            "SocialList":619,
            "IslandWorkshopSupplyDemand":864,
            "RSV":570,
            "RSF":860,
            "WorldVisitQueue":679
        },
        "ClientZoneIpcType":{
            "ActionRequest":865,
            "ActionRequestGroundTargeted":738,
            "ChatHandler":375,
            "ClientTrigger":868,
            "InventoryModifyHandler":318,
            "MarketBoardPurchaseHandler":984,
            "MarketBoardRequestItemListingInfo":528,
            "SetSearchInfoHandler":420,
            "UpdatePositionHandler":561,
            "UpdatePositionInstance":627,
            "Heartbeat":466,
            "WorldTravel":917,
            "ClientCountdownInitiate":626
        }
    }
}